[
    {
      "id": "brotato",
      "titulo": "Brotato",
      "fecha": "10-04-25",
      "version": "1.1.10.2a",
      "peso": "200 MB",
      "plataforma": "PC",
      "descripcion": "Brotato es un roguelite de disparos en el que te moverás de arriba abajo del escenario. Encarna a una patata con 6 armas simultáneas para hacer frente a los alienígenas. Elige entre una variedad de características y objetos para crear combinaciones únicas y sobrevivir hasta que acudan los refuerzos.",
      "imagen": "assets/brotato.jpg",
      "requisitos": "...",
      "pass": "No tiene",
      "categorias": ["b-r","supervivencia", "multijugador", "arcade","accion","casual"],
      "link": "https://ouo.io/BpNHAjv"
    },
    {
      "id": "alice-madness-returns",
      "titulo": "Alice madness returns",
      "fecha": "10-04-25",
      "version": "...",
      "peso": "5.60 GB",
      "plataforma": "PC",
      "descripcion": "Alice: Madness Returns es un videojuego de plataformas y acción con toques góticos desde una perspectiva en tercera persona, con ataques y combos fáciles de usar parecidos a las series de Devil May Cry y a Splatterhouse de 2010. La diferencia es que no se pueden ejecutar combos de ataque aéreos.",
      "imagen": "assets/alicemadness.jpg",
      "requisitos": "...",
      "pass": "No tiene",
      "categorias": ["b-r","terror", "plataforma", "accion","aventura"],
      "link": "https://ouo.io/EBLUYo"
    },
    {
      "id": "schedule-i",
      "titulo": "Schedule I",
      "fecha": "10-04-25",
      "version": "0.3.3f14",
      "peso": "1.88 GB",
      "plataforma": "PC",
      "descripcion": "Desde un pequeño traficante hasta un capo, fabrica y distribuye una amplia gama de drogas por el descuidado pueblo de Hyland Point. Expande tu imperio con propiedades, negocios, empleados y mucho más.",
      "imagen": "assets/schedule.jpg",
      "requisitos": "...",
      "pass": "No tiene",
      "categorias": ["m-r","simulacion", "accion", "mundoabierto","aventura"],
      "link": "https://ouo.io/Oj3McGa"
    },
    {
        "id": "geometry-dash",
        "titulo": "Geometry Dash",
        "fecha": "10-04-25",
        "version": "2.207",
        "peso": "300 MB",
        "plataforma": "PC",
        "descripcion": "Geometry Dash (anteriormente llamado 'Geometry Jump') es un videojuego de plataformas y videojuego rítmico creado en 2013 por el desarrollador sueco Robert Topala (más conocido como RobTop), y posteriormente desarrollado por su empresa independiente RobTop Games.",
        "imagen": "assets/geometry dash.jpg",
        "requisitos": "...",
        "pass": "No tiene",
        "categorias": ["b-r","plataforma", "arcade", "casual"],
        "link": "https://ouo.io/KXNYHvM"
    }
]